pytorchtrainer/__init__.py
pytorchtrainer/main.py
pytorchtrainer/trainer.py
pytorchtrainer/utils.py
pytorchtrainer/callback/__init__.py
pytorchtrainer/callback/callback.py
pytorchtrainer/callback/checkpoint.py
pytorchtrainer/callback/file_writer.py
pytorchtrainer/callback/metric.py
pytorchtrainer/callback/validation.py
pytorchtrainer/metric/__init__.py
pytorchtrainer/metric/accuracy.py
pytorchtrainer/metric/mean_absolute_error.py
pytorchtrainer/metric/torch_loss.py
pytorchtrainer/stop_condition/__init__.py
pytorchtrainer/stop_condition/early_stopping.py
pytorchtrainer-0.2.1.dist-info/LICENSE
pytorchtrainer-0.2.1.dist-info/METADATA
pytorchtrainer-0.2.1.dist-info/WHEEL
pytorchtrainer-0.2.1.dist-info/top_level.txt
pytorchtrainer-0.2.1.dist-info/RECORD
