Metadata-Version: 2.1
Name: pytorchtrainer
Version: 0.2.1
Summary: PyTorch module trainer
Home-page: https://github.com/benoitmartin88/pytorchtrainer
Author: Benoit Martin
Author-email: benoitmartin88.pro@gmail.com
License: MIT
Project-URL: Source, https://github.com/benoitmartin88/pytorchtrainer
Project-URL: Bug Reports, https://github.com/benoitmartin88/pytorchtrainer/issues
Keywords: pytorch trainer
Platform: UNKNOWN
Classifier: Programming Language :: Python :: 3
Classifier: License :: OSI Approved :: MIT License
Classifier: Operating System :: OS Independent
Requires-Python: >=3.5
Requires-Dist: torch (>=1.0.0)
